<DOMSymbolItem xmlns:xsi="http://www.w3.org/2001/XMLSchema-instance" xmlns="http://ns.adobe.com/xfl/2008/" name="Graphic/shape 625" itemID="4debac18-00000272" symbolType="graphic" lastModified="1307290648">
  <timeline>
    <DOMTimeline name="shape 625">
      <layers>
        <DOMLayer name="Layer 1" color="#FFFF00" current="true" isSelected="true">
          <frames>
            <DOMFrame index="0" motionTweenScale="false" keyMode="8192">
              <elements>
                <DOMShape selected="true" isFloating="true">
                  <fills>
                    <FillStyle index="1">
                      <SolidColor color="#DDE5EB"/>
                    </FillStyle>
                    <FillStyle index="2">
                      <SolidColor color="#B2BBC5"/>
                    </FillStyle>
                    <FillStyle index="3">
                      <SolidColor color="#F2F9FC"/>
                    </FillStyle>
                    <FillStyle index="4">
                      <SolidColor color="#FBFFFF"/>
                    </FillStyle>
                  </fills>
                  <edges>
                    <Edge fillStyle1="1" edges="!3325 3240|3310 3000!3310 3000|3315 2655!3315 2655|3355 2295!3355 2295|3415 2080!3415 2080|3490 1950!3490 1950|3510 1925!3510 1925|3620 1895!3620 1895|6170 1690!6170 1690|6845 1660!6845 1660|7565 1605!7565 1605|8210 1575!8210 1575|8535
 1575!8535 1575|8805 1550!8805 1550|10030 1515!10030 1515|12315 1505!12315 1505|14265 1550!14265 1550|16475 1660!16475 1660|17840 1755!17840 1755|19445 1895!19445 1895|19545 1925!19545 1925|19630 2060!19630 2060|19695 2285!19695 2285
|19740 2740!19740 2740|19745 2955!19745 2955|19725 3250"/>
                    <Edge fillStyle1="2" edges="
!19725 3250|20455 3095!20455 3095|20550 3090!20550 3090|20635 3120!20635 3120|20675 3180!20675 3180|20700 3520!20700 3520|20685 4055!20685 4055|20650 4340!20650 4340|20600 4585!20600 4585|20535 4820!20535 4820|20445 5040!20445 5040|20335
 5225!20335 5225|20220 5330!20220 5330|20120 5360!20120 5360|19605 5425"/>
                    <Edge fillStyle1="3" edges="
!19605 5425|19640 5790!19640 5790|19740 6495!19740 6495|19885 7180!19885 7180|20015 7645!20015 7645|20150 8020!20150 8020|20360 8440!20360 8440|20510 8645!20510 8645|20600 8740!20600 8740|20730 8830!20730 8830|20735 8850!20735 8850|20695
 8875!20695 8875|20580 8905!20580 8905|19805 9030"/>
                    <Edge fillStyle1="4" edges="
!19805 9030|19875 9635!19875 9635|19995 10450!19995 10450|19990 10550!19990 10550|19955 10615!19955 10615|19895 10655!19895 10655|19820 10670!19820 10670|13520 10625!13520 10625|8535 10630!8535 10630|3225 10670!3225 10670|3155 10655!3155
 10655|3095 10610!3095 10610|3060 10545!3060 10545|3060 10430!3060 10430|3165 9730!3165 9730|3245 9025"/>
                    <Edge fillStyle1="3" edges="
!3245 9025|2410 8885!2410 8885|2325 8845!2325 8845|2330 8825!2330 8825|2445 8745!2445 8745|2560 8625!2560 8625|2690 8445!2690 8445|2905 8015!2905 8015|3030 7670!3030 7670|3175 7160!3175 7160|3310 6500!3310 6500|3410 5795!3410 5795|3445
 5420"/>
                    <Edge fillStyle1="2" edges="
!3445 5420|2950 5360!2950 5360|2835 5325!2835 5325|2735 5235!2735 5235|2625 5070!2625 5070|2545 4880!2545 4880|2465 4610!2465 4610|2385 4135!2385 4135|2360 3790!2360 3790|2365 3405!2365 3405|2385 3185!2385 3185|2405 3130!2405 3130|2440
 3105!2440 3105|2500 3085!2500 3085|2615 3090!2615 3090|3325 3240"/>
                    <Edge fillStyle0="2" fillStyle1="1" edges="
!19725 3250|18445 3485!18445 3485|17755 3590!17755 3590|16460 3755!16460 3755|14735 3910!14735 3910|13615 3975!13615 3975|12330 4010!12330 4010|11605 4014"/>
                    <Edge fillStyle0="2" edges="
!11605 4014|11170 4020!11170 4020|10770 4010"/>
                    <Edge fillStyle0="2" fillStyle1="1" edges="
!10770 4010|9265 3965!9265 3965|7980 3880!7980 3880|6855 3780!6855 3780|6000 3680!6000 3680|4925 3530!4925 3530|4175 3405!4175 3405|3325 3240"/>
                    <Edge fillStyle0="3" fillStyle1="2" edges="
!19605 5425|17460 5695!17460 5695|16455 5805!16455 5805|15080 5930!15080 5930|13965 6005!13965 6005|12930 6050!12930 6050|11975 6070!11975 6070|10770 6065!10770 6065|9635 6030!9635 6030|7690 5905!7690 5905|5880 5725!5880 5725|3445 5420"/>
                    <Edge fillStyle0="4" fillStyle1="3" edges="
!19805 9030|17970 9290!17970 9290|16755 9425!16755 9425|15425 9540!15425 9540|13535 9645!13535 9645|12455 9675!12455 9675|10970 9680!10970 9680|9435 9640!9435 9640|8500 9595!8500 9595|7415 9520!7415 9520|5625 9350!5625 9350|4720 9240
!4720 9240|3245 9025"/>
                    <Edge fillStyle0="1" edges="
!10770 4010|11605 4014"/>
                  </edges>
                </DOMShape>
              </elements>
            </DOMFrame>
          </frames>
        </DOMLayer>
      </layers>
    </DOMTimeline>
  </timeline>
</DOMSymbolItem>